idenpy/__init__.py
idenpy/main.py
idenpy-0.0.0.dist-info/METADATA
idenpy-0.0.0.dist-info/WHEEL
idenpy-0.0.0.dist-info/top_level.txt
idenpy-0.0.0.dist-info/RECORD
