Metadata-Version: 2.1
Name: idenpy
Version: 0.0.0
Summary: Coming soon, before July 2025
Author-email: seyed zuhair bolourchian tabrizi <zuhairtabrizi@gmail.com>
